[
  {
    "category_id": 1,
    "category_name_zh": "美食",
    "category_name_en": "Food",
    "amap_types": "050000",
    "amap_keywords": ["成都餐厅", "成都火锅", "成都川菜", "成都小吃", "成都串串", "成都烧烤", "成都冒菜", "成都兔头", "成都面馆", "成都咖啡", "成都茶馆", "成都甜品", "成都西餐", "成都日料", "成都私房菜", "成都老字号", "成都苍蝇馆子"],
    "description": "成都美食门店，覆盖火锅/川菜/串串/小吃/老字号及各地菜系"
  },
  {
    "category_id": 2,
    "category_name_zh": "酒店",
    "category_name_en": "Hotel",
    "amap_types": "100000",
    "amap_keywords": ["成都酒店", "成都民宿", "成都青年旅舍", "成都五星级酒店", "成都精品酒店", "成都连锁酒店", "成都宽窄巷子民宿", "成都锦里民宿", "成都度假村", "成都温泉酒店"],
    "description": "成都住宿服务，覆盖星级酒店/民宿/客栈/青年旅舍"
  },
  {
    "category_id": 3,
    "category_name_zh": "景点",
    "category_name_en": "Attraction",
    "amap_types": "110000|140000",
    "amap_keywords": ["成都景区", "成都博物馆", "成都公园", "成都寺庙", "成都熊猫基地", "成都宽窄巷子", "成都锦里", "成都杜甫草堂", "成都武侯祠", "成都青城山", "成都都江堰", "成都美术馆", "成都游乐园", "成都主题公园"],
    "description": "成都旅游景点，覆盖5A/4A景区/博物馆/公园/寺庙/主题乐园"
  },
  {
    "category_id": 4,
    "category_name_zh": "购物",
    "category_name_en": "Shopping",
    "amap_types": "060100",
    "amap_keywords": ["成都购物中心", "成都百货商场", "成都春熙路", "成都太古里", "成都IFS", "成都免税店", "成都奥特莱斯", "成都商圈", "成都特产店", "成都文创店"],
    "description": "成都购物场所，覆盖商圈百货/特色街区/免税店/文创市集"
  },
  {
    "category_id": 5,
    "category_name_zh": "娱乐",
    "category_name_en": "Entertainment",
    "amap_types": "080500",
    "amap_keywords": ["成都酒吧", "成都KTV", "成都密室逃脱", "成都剧本杀", "成都电影院", "成都剧院", "成都Livehouse", "成都夜店", "成都相声", "成都川剧变脸", "成都茶馆表演", "成都桌游", "成都电竞", "成都水疗", "成都温泉"],
    "description": "成都娱乐场所，覆盖酒吧/KTV/密室/剧本杀/演出/川剧/夜店"
  }
]
